pycsvjson/__init__.py
pycsvjson/pycsvjson.py
pycsvjson-0.0.5.dist-info/AUTHORS
pycsvjson-0.0.5.dist-info/LICENSE
pycsvjson-0.0.5.dist-info/METADATA
pycsvjson-0.0.5.dist-info/WHEEL
pycsvjson-0.0.5.dist-info/entry_points.txt
pycsvjson-0.0.5.dist-info/top_level.txt
pycsvjson-0.0.5.dist-info/RECORD
