Metadata-Version: 2.1
Name: pycsvjson
Version: 0.0.5
Summary: A utility to transform CSV files into structured JSON
Home-page: https://github.com/TemboInc/pycsvjson
Author: Tembo Inc.
Author-email: devsupport@temboinc.com
License: MIT License
Platform: UNKNOWN
Classifier: Development Status :: 3 - Alpha
Classifier: License :: OSI Approved :: MIT License
Classifier: Programming Language :: Python :: 3
Requires-Dist: beautifulsoup4
Requires-Dist: boltons
Requires-Dist: jsonmapping (>=0.7.4)
Requires-Dist: pip (>=9.0.0)
Requires-Dist: tqdm
Requires-Dist: ujson
